pyrefo/__init__.py
pyrefo/_refo.abi3.so
pyrefo/inst.py
pyrefo/match.py
pyrefo/patterns.py
pyrefo/pike.c
pyrefo/pyrefo_build.py
pyrefo/regexp.h
pyrefo/sub.c
pyrefo/tests/__init__.py
pyrefo/tests/test_match.py
pyrefo-0.4.dist-info/LICENSE.txt
pyrefo-0.4.dist-info/METADATA
pyrefo-0.4.dist-info/WHEEL
pyrefo-0.4.dist-info/top_level.txt
pyrefo-0.4.dist-info/RECORD
