Metadata-Version: 2.1
Name: pyrefo
Version: 0.4
Summary: a fast regex for object
Home-page: http://github.com/yimian/pyrefo
Author: zhangjinjie
Author-email: zhangjinjie@yimian.com.cn
License: GPLv3+
Keywords: regex
Platform: UNKNOWN
Classifier: Development Status :: 3 - Alpha
Classifier: License :: OSI Approved :: GNU Lesser General Public License v3 or later (LGPLv3+)
Classifier: Programming Language :: Python :: 2.7
Classifier: Programming Language :: Python :: 3.5
Classifier: Programming Language :: Python :: 3.6
Classifier: Programming Language :: Python :: 3.7
Classifier: Topic :: Text Processing :: Linguistic
Requires-Dist: cffi (>=1.0.0)
